rin/jsonutils/__init__.py
rin/jsonutils/_coder_switch.py
rin/jsonutils/advanced_json_encoder.py
rin/jsonutils/resolvers.py
rin/jsonutils/typing.py
rin_jsonutils-1.1.0.dist-info/LICENSE
rin_jsonutils-1.1.0.dist-info/METADATA
rin_jsonutils-1.1.0.dist-info/WHEEL
rin_jsonutils-1.1.0.dist-info/top_level.txt
rin_jsonutils-1.1.0.dist-info/RECORD
