Metadata-Version: 2.1
Name: rin-jsonutils
Version: 1.1.0
Summary: Add custom JSON coders and provide functions to set and get the default json coders
License: MIT License
Project-URL: GitHub, https://github.com/susautw/rin-jsonutils
Keywords: json,utils
Classifier: Programming Language :: Python :: 3
Classifier: License :: OSI Approved :: MIT License
Classifier: Operating System :: OS Independent
Requires-Python: >=3.6
License-File: LICENSE
Provides-Extra: numpy
Requires-Dist: numpy ; extra == 'numpy'
